graphlot/__init__.py
graphlot/graphlot.py
graphlot-0.3.2.dist-info/licenses/LICENSE.txt
graphlot-0.3.2.dist-info/METADATA
graphlot-0.3.2.dist-info/WHEEL
graphlot-0.3.2.dist-info/top_level.txt
graphlot-0.3.2.dist-info/RECORD
