Metadata-Version: 2.4
Name: graphlot
Version: 0.3.2
Author: Francesco Gualdi
License: GPL
License-File: LICENSE.txt
Requires-Dist: networkx
Requires-Dist: igraph
Requires-Dist: textalloc
Requires-Dist: matplotlib
Dynamic: author
Dynamic: description
Dynamic: description-content-type
Dynamic: license
Dynamic: license-file
Dynamic: requires-dist
